proxyverse/__init__.py
proxyverse/api/__init__.py
proxyverse/api/api_methods.py
proxyverse/api/base_api.py
proxyverse/api/get_api.py
proxyverse/api/post_api.py
proxyverse/enums/__init__.py
proxyverse/enums/api_key.py
proxyverse/enums/countries.py
proxyverse/enums/generate_list.py
proxyverse/enums/users.py
proxyverse/exceptions/__init__.py
proxyverse/exceptions/bad_request.py
proxyverse/exceptions/forbidden.py
proxyverse/exceptions/gateway_timeout.py
proxyverse/exceptions/gone.py
proxyverse/exceptions/http_exception.py
proxyverse/exceptions/internal_server_error.py
proxyverse/exceptions/proxy_auth_required.py
proxyverse/exceptions/too_many_requests.py
proxyverse-0.1.1.dist-info/LICENSE
proxyverse-0.1.1.dist-info/METADATA
proxyverse-0.1.1.dist-info/WHEEL
proxyverse-0.1.1.dist-info/top_level.txt
proxyverse-0.1.1.dist-info/RECORD
