Metadata-Version: 2.1
Name: proxyverse
Version: 0.1.1
Summary: A Python package for interacting with the Proxyverse API
Home-page: https://github.com/alexkorolex/ProxyVerse-Python
Download-URL: https://github.com/alexkorolex/ProxyVerse-Python/archive/refs/heads/master.zip
Author: alexkorolex
Author-email: alexkorolex@bk.ru
License: MIT
Classifier: Programming Language :: Python :: 3
Classifier: Programming Language :: Python :: 3.11
Classifier: License :: OSI Approved :: MIT License
Classifier: Operating System :: OS Independent
Requires-Python: >=3.11
License-File: LICENSE
Requires-Dist: httpx >=0.27.0
